pyzbc2014/__init__.py
pyzbc2014/pyzbc2014.py
pyzbc2014/_lib/__init__.py
pyzbc2014/_lib/dummy.c
pyzbc2014/_lib/dummy_ext_for_platlib.cp314-win32.pyd
pyzbc2014/_lib/libzbc2014.dll
pyzbc2014/model/__init__.py
pyzbc2014/model/complex.c
pyzbc2014/model/complex.h
pyzbc2014/model/complex.hpp
pyzbc2014/model/model_IHC.c
pyzbc2014/model/model_Synapse.c
pyzbc2014/model/stub.py
pyzbc2014-0.0.2.dist-info/licenses/LICENSE
pyzbc2014-0.0.2.dist-info/METADATA
pyzbc2014-0.0.2.dist-info/WHEEL
pyzbc2014-0.0.2.dist-info/top_level.txt
pyzbc2014-0.0.2.dist-info/RECORD
