Metadata-Version: 2.4
Name: pyzbc2014
Version: 0.0.2
Summary: Simple Python 3 wrapper for the Zilany, Bruce, and Carney (2014) auditory nerve model.
Author-email: Daniel Guest <daniel_guest@urmc.rochester.edu>, Thomas Stoll <tomstoll@med.umich.edu>
License:                     GNU AFFERO GENERAL PUBLIC LICENSE
Keywords: auditory,nerve,model,zilany,bruce,carney,2014
Requires-Python: >=3.10
License-File: LICENSE
Requires-Dist: numpy>=1.21.0
Requires-Dist: scipy>=1.7.2
Dynamic: license-file
